space_objects_geos/__init__.py
space_objects_geos/outputs.py
space_objects_geos-1.2.0.dist-info/LICENSE
space_objects_geos-1.2.0.dist-info/WHEEL
space_objects_geos-1.2.0.dist-info/METADATA
space_objects_geos-1.2.0.dist-info/RECORD
