Metadata-Version: 2.1
Name: space-objects-geos
Version: 1.2.0
Summary: Provide space_objects output geometry capabilities like shapely geometry and geojson.
Author: larrieu olivier
Author-email: larrieuolivierad@gmail.com
Requires-Python: >=3.10,<4.0
Classifier: Programming Language :: Python :: 3
Classifier: Programming Language :: Python :: 3.10
Classifier: Programming Language :: Python :: 3.11
Requires-Dist: geojson (>=2.5.0,<3.0.0)
Requires-Dist: shapely (>=1.8.5.post1,<2.0.0)
Requires-Dist: space-objects (>=1.5.0,<2.0.0)
